git_redmine.py
git_redmine-1.1.0.dist-info/METADATA
git_redmine-1.1.0.dist-info/WHEEL
git_redmine-1.1.0.dist-info/entry_points.txt
git_redmine-1.1.0.dist-info/top_level.txt
git_redmine-1.1.0.dist-info/RECORD
