Metadata-Version: 2.1
Name: git-redmine
Version: 1.1.0
Summary: Git porcelain to interface with Redmine
Home-page: https://dev.entrouvert.org/projects/git-redmine/
Author: Benjamin Dauvergne
Author-email: bdauvergne@entrouvert.com
License: UNKNOWN
Platform: UNKNOWN
Requires-Dist: Click
Requires-Dist: GitPython
Requires-Dist: Unidecode
Requires-Dist: python-redmine
Requires-Dist: requests
